{
  "url": "https://bright-al-ahsa-clinic.vercel.app/doctors",
  "title": "Clinicians — Bright Specialized Clinics — Bright Specialized Clinics",
  "h1": [
    "Named clinicians.Verifiable credentials."
  ],
  "headings": [
    "Named clinicians.Verifiable credentials.",
    "Dr. Hassan Nazzal",
    "Dr. Marina Naddaf",
    "Dr. Doaa Goda",
    "Dr. Nadeen Kabboura",
    "Dr. Amirah Mohannadi",
    "Dr. Dina Abdul Halim",
    "Not sure which department fits?"
  ],
  "links": [
    {
      "text": "Skip to content",
      "href": "https://bright-al-ahsa-clinic.vercel.app/doctors#main"
    },
    {
      "text": "Reserve Eid time →",
      "href": "https://bright-al-ahsa-clinic.vercel.app/booking"
    },
    {
      "text": "",
      "href": "https://bright-al-ahsa-clinic.vercel.app/"
    },
    {
      "text": "Departments",
      "href": "https://bright-al-ahsa-clinic.vercel.app/services"
    },
    {
      "text": "Our Clinicians",
      "href": "https://bright-al-ahsa-clinic.vercel.app/doctors"
    },
    {
      "text": "Branches",
      "href": "https://bright-al-ahsa-clinic.vercel.app/about"
    },
    {
      "text": "Trust",
      "href": "https://bright-al-ahsa-clinic.vercel.app/trust"
    },
    {
      "text": "Journal",
      "href": "https://bright-al-ahsa-clinic.vercel.app/journal"
    },
    {
      "text": "Contact",
      "href": "https://bright-al-ahsa-clinic.vercel.app/booking"
    },
    {
      "text": "Book on WhatsApp",
      "href": "https://wa.me/966557337555"
    },
    {
      "text": "Book",
      "href": "https://wa.me/966557337555"
    },
    {
      "text": "Book on WhatsApp",
      "href": "https://wa.me/966557337555"
    },
    {
      "text": "",
      "href": "https://bright-al-ahsa-clinic.vercel.app/"
    },
    {
      "text": "Dermatology & Laser",
      "href": "https://bright-al-ahsa-clinic.vercel.app/services"
    },
    {
      "text": "Plastic Surgery",
      "href": "https://bright-al-ahsa-clinic.vercel.app/services"
    },
    {
      "text": "Cosmetic Dentistry",
      "href": "https://bright-al-ahsa-clinic.vercel.app/services"
    },
    {
      "text": "OB/GYN",
      "href": "https://bright-al-ahsa-clinic.vercel.app/services"
    },
    {
      "text": "Paediatrics",
      "href": "https://bright-al-ahsa-clinic.vercel.app/services"
    },
    {
      "text": "Bariatric Surgery",
      "href": "https://bright-al-ahsa-clinic.vercel.app/services"
    },
    {
      "text": "About",
      "href": "https://bright-al-ahsa-clinic.vercel.app/about"
    },
    {
      "text": "Our Clinicians",
      "href": "https://bright-al-ahsa-clinic.vercel.app/doctors"
    },
    {
      "text": "Trust & Credentials",
      "href": "https://bright-al-ahsa-clinic.vercel.app/trust"
    },
    {
      "text": "Journal",
      "href": "https://bright-al-ahsa-clinic.vercel.app/journal"
    },
    {
      "text": "Book on WhatsApp",
      "href": "https://bright-al-ahsa-clinic.vercel.app/booking"
    },
    {
      "text": "Visit us · Al Hada",
      "href": "https://bright-al-ahsa-clinic.vercel.app/about"
    },
    {
      "text": "Call 920024428",
      "href": "tel:920024428"
    },
    {
      "text": "WhatsApp 0557337555",
      "href": "https://wa.me/966557337555"
    },
    {
      "text": "✦Vision 2030aligned",
      "href": "https://www.vision2030.gov.sa/"
    },
    {
      "text": "Privacy",
      "href": "https://bright-al-ahsa-clinic.vercel.app/privacy"
    },
    {
      "text": "Terms",
      "href": "https://bright-al-ahsa-clinic.vercel.app/terms"
    },
    {
      "text": "Accessibility",
      "href": "https://bright-al-ahsa-clinic.vercel.app/accessibility"
    },
    {
      "text": "☏",
      "href": "tel:920024428"
    },
    {
      "text": "✦Book on WhatsApp",
      "href": "https://wa.me/966557337555"
    }
  ],
  "media": [
    {
      "tag": "img",
      "alt": "Bright Medical Center",
      "src": "https://bright-al-ahsa-clinic.vercel.app/_next/image?url=%2Fbrand%2Fbright-logo.png&w=640&q=75",
      "poster": ""
    },
    {
      "tag": "img",
      "alt": "Bright Medical Center",
      "src": "https://bright-al-ahsa-clinic.vercel.app/_next/image?url=%2Fbrand%2Fbright-logo.png&w=640&q=75",
      "poster": ""
    }
  ],
  "portraitPlaceholders": 7,
  "sections": [
    {
      "index": 0,
      "tag": "nav",
      "id": "top",
      "className": "sticky top-0 z-50",
      "heading": "",
      "text": "Departments Our Clinicians Branches Trust Journal Contact BOOK ON WHATSAPP",
      "portraitCount": 0,
      "imgCount": 1,
      "videoCount": 0
    },
    {
      "index": 1,
      "tag": "section",
      "id": "",
      "className": "",
      "heading": "Named clinicians.Verifiable credentials.",
      "text": "Chapter I. ✦ OUR CLINICIANS Named clinicians. Verifiable credentials. Six specialist physicians and a full medical team under one roof in Al Khobar. Every name listed here is publicly verifiable.",
      "portraitCount": 1,
      "imgCount": 0,
      "videoCount": 0
    },
    {
      "index": 2,
      "tag": "section",
      "id": "",
      "className": "section",
      "heading": "Maxillofacial Surgery · Senior partner",
      "text": "MAXILLOFACIAL SURGERY · SENIOR PARTNER Dr. Hassan Nazzal Jordanian Board–certified maxillofacial surgeon with Fellowship from the Royal College of Surgeons in Ireland. Senior partner of Bright Specialized Clinics since the early years. — MD · Jordanian Board of Maxillofacial Surgery — FRCS · Royal College of Surgeons in Ireland — Senior partner · Bright Specialized Clinics SENIOR DERMATOLOGY · LASER SPECIALIST Dr. Marina Naddaf American Academy of Dermatology member since 2004. Canadian Laser Diploma. Twenty-five years of patient care across the Gulf — quiet results, never theatrical. — MD · MSc Dermatology — AAD member since 2004 — Canadian Laser Diploma — 25+ years in practice COSMETIC AESTHETICS · INJECTABLES Dr. Doaa Goda Specialist in fillers, Botox, and body cosmetic procedures. Patient-favourite for natural, undetectable results. — MD · Cosmetic Aesthetics — Filler & Botox specialist OB/GYN · INTIMATE HEALTH Dr. Nadeen Kabboura Consultant in gynecology and intimate health. Provides discreet, women-only consultations. — MD · OB/GYN Consultant AESTHETIC INJECTABLES · LIP WORK Dr",
      "portraitCount": 6,
      "imgCount": 0,
      "videoCount": 0
    },
    {
      "index": 3,
      "tag": "section",
      "id": "",
      "className": "section section-dark",
      "heading": "Not sure which department fits?",
      "text": "Not sure which department fits? WhatsApp us — we will help you book with the right specialist. BOOK ON WHATSAPP",
      "portraitCount": 0,
      "imgCount": 0,
      "videoCount": 0
    },
    {
      "index": 4,
      "tag": "footer",
      "id": "",
      "className": "",
      "heading": "Departments",
      "text": "Ten specialty departments. One quiet roof in Al Khobar. One promise: excellence as the only standard. MOH LICENSED AL KHOBAR · EASTERN PROVINCE DEPARTMENTS Dermatology & Laser Plastic Surgery Cosmetic Dentistry OB/GYN Paediatrics Bariatric Surgery THE CLINIC About Our Clinicians Trust & Credentials Journal REACH US Book on WhatsApp Visit us · Al Hada Call 920024428 WhatsApp 0557337555 © 2026 Bright Specialized Clinics — Bright Specialized Clinics — Al-Maha Bright Skin Medical Complex. ✦ VISION 2030 aligned Privacy·Terms·Accessibility",
      "portraitCount": 0,
      "imgCount": 1,
      "videoCount": 0
    }
  ],
  "bodyText": "Skip to content ✦ EID AL-ADHA — FAST-TRACK BOOKING — 19 days until Eid. Slots filling — same-day confirmation. 14 days · 5 hours RESERVE EID TIME → Departments Our Clinicians Branches Trust Journal Contact BOOK ON WHATSAPP Chapter I. ✦ OUR CLINICIANS Named clinicians. Verifiable credentials. Six specialist physicians and a full medical team under one roof in Al Khobar. Every name listed here is publicly verifiable. MAXILLOFACIAL SURGERY · SENIOR PARTNER Dr. Hassan Nazzal Jordanian Board–certified maxillofacial surgeon with Fellowship from the Royal College of Surgeons in Ireland. Senior partner of Bright Specialized Clinics since the early years. — MD · Jordanian Board of Maxillofacial Surgery — FRCS · Royal College of Surgeons in Ireland — Senior partner · Bright Specialized Clinics SENIOR DERMATOLOGY · LASER SPECIALIST Dr. Marina Naddaf American Academy of Dermatology member since 2004. Canadian Laser Diploma. Twenty-five years of patient care across the Gulf — quiet results, never theatrical. — MD · MSc Dermatology — AAD member since 2004 — Canadian Laser Diploma — 25+ years in practice COSMETIC AESTHETICS · INJECTABLES Dr. Doaa Goda Specialist in fillers, Botox, and body cosmetic procedures. Patient-favourite for natural, undetectable results. — MD · Cosmetic Aesthetics — Filler & Botox specialist OB/GYN · INTIMATE HEALTH Dr. Nadeen Kabboura Consultant in gynecology and intimate health. Provides discreet, women-only consultations. — MD · OB/GYN Consultant AESTHETIC INJECTABLES · LIP WORK Dr. Amirah Mohannadi Specialist in lip filler artistry. Known for restrained volumes that respect natural facial proportions. — MD · Aesthetic Medicine AESTHETIC DERMATOLOGY · MICROBLADING Dr. Dina Abdul Halim Specialist in microblading, Botox, and aesthetic dermatology procedures. Detail-oriented practitioner with a precision-first approach. — MD · Aesthetic Dermatology — Microblading & Botox specialist Not sure which department fits? WhatsApp us — we will help you book with the right specialist. BOOK ON WHATSAPP Ten specialty departments. One quiet roof in Al Khobar. One promise: excellence as the only standard. MOH LICENSED AL KHOBAR · EASTERN PROVINCE DEPARTMENTS Dermatology & Laser Plastic Surgery Cosmetic Dentistry OB/GYN Paediatrics Bariatric Surgery THE CLINIC About Our Clinicians Trust & Credentials Journal REACH US Book on WhatsApp Visit us · Al Hada Call 920024428 WhatsApp 0557337555 © 2026 Bright Specialized Clinics — Bright Specialized Clinics — Al-Maha Bright Skin Medical Complex. ✦ VISION 2030 aligned Privacy·Terms·Accessibility ✦ Ask Bright",
  "scrollHeight": 2637
}